easyparse/__init__.py
easyparse/export.py
easyparse/pkg/__init__.py
easyparse/pkg/xml_to_json_handler.py
easyparse/tests/fixtures/__init__.py
easyparse/tests/fixtures/import_samples.py
easy_parse-0.1.1.dist-info/METADATA
easy_parse-0.1.1.dist-info/WHEEL
easy_parse-0.1.1.dist-info/top_level.txt
easy_parse-0.1.1.dist-info/RECORD
