Metadata-Version: 2.1
Name: easy-parse
Version: 0.1.1
Summary: Easy parsing for xml and json
Home-page: https://github.com/uncmath25/easy-parse
Author: Colton Willig
Author-email: coltonwillig@gmail.com
License: MIT
Platform: UNKNOWN
Requires-Python: >=3.6
